langgate/client/__init__.py
langgate/client/http.py
langgate/client/protocol.py
langgate/client/py.typed
langgate_client-0.3.3.dist-info/METADATA
langgate_client-0.3.3.dist-info/WHEEL
langgate_client-0.3.3.dist-info/RECORD
