Metadata-Version: 2.4
Name: langgate-client
Version: 0.3.3
Summary: HTTP Client for LangGate AI Gateway
Author: Tanantor Ltd.
Maintainer-email: Saran Connoly <saran@tanantor.com>
License: MIT
Requires-Python: >=3.13
Requires-Dist: httpx<0.29.0,>=0.28.1
Requires-Dist: langgate-core==0.3.3
